[
  {
    "rank": 1,
    "product_id": "145628",
    "title": "惑溺のアンドロマリウス ～Codename: Null～【出演声優：佐和真中】",
    "voice_actor": "佐和真中",
    "tags": [
      "NEW",
      "シチュエーションCD",
      "特典あり"
    ],
    "thumb_url": "https://pokedora.com/get_image.php?product_id=145628",
    "work_url": "https://pokedora.com/products/detail.php?product_id=145628"
  },
  {
    "rank": 2,
    "product_id": "116723",
    "title": "ポリス旦那さま-爆発物処理班・三葉修志-【出演声優：テトラポット登】",
    "voice_actor": "テトラポット登",
    "tags": [
      "シチュエーションCD",
      "割引",
      "特典あり"
    ],
    "thumb_url": "https://pokedora.com/get_image.php?product_id=116723",
    "work_url": "https://pokedora.com/products/detail.php?product_id=116723"
  },
  {
    "rank": 3,
    "product_id": "147451",
    "title": "おとなり以上、恋人未満 ～激メロ営業部長・城の寵愛～【出演声優：茶介】",
    "voice_actor": "茶介",
    "tags": [
      "配信限定シチュエーション",
      "特典あり"
    ],
    "thumb_url": "https://pokedora.com/get_image.php?product_id=147451",
    "work_url": "https://pokedora.com/products/detail.php?product_id=147451"
  },
  {
    "rank": 4,
    "product_id": "146592",
    "title": "それはささやかな恋のはじまり 綿矢翔真【出演声優：彩和矢】",
    "voice_actor": "彩和矢",
    "tags": [
      "NEW",
      "配信限定シチュエーション",
      "特典あり"
    ],
    "thumb_url": "",
    "work_url": "https://pokedora.com/products/detail.php?product_id=146592"
  },
  {
    "rank": 5,
    "product_id": "116732",
    "title": "ポリス旦那さま-サイバー犯罪捜査官・如月瑛智-【出演声優：土門熱】",
    "voice_actor": "土門熱",
    "tags": [
      "シチュエーションCD",
      "割引",
      "特典あり"
    ],
    "thumb_url": "",
    "work_url": "https://pokedora.com/products/detail.php?product_id=116732"
  },
  {
    "rank": 6,
    "product_id": "148089",
    "title": "《配信開始は2026年6月26日0:00》先生、痛くしないでOmnibusStory 『源慧史～おはようからおやすみまで～』【出演声優：茶介】",
    "voice_actor": "茶介",
    "tags": [
      "NEW",
      "配信限定シチュエーション",
      "割引"
    ],
    "thumb_url": "",
    "work_url": "https://pokedora.com/products/detail.php?product_id=148089"
  },
  {
    "rank": 7,
    "product_id": "146889",
    "title": "《絶倫×耐久×ライバル同僚》Ｗｈｉｃｈ？【出演声優：冬ノ熊肉】",
    "voice_actor": "冬ノ熊肉",
    "tags": [
      "配信限定シチュエーション",
      "特典あり"
    ],
    "thumb_url": "",
    "work_url": "https://pokedora.com/products/detail.php?product_id=146889"
  },
  {
    "rank": 8,
    "product_id": "112534",
    "title": "ポリス旦那さま-刑事・久遠弘都-【出演声優：冬ノ熊肉】",
    "voice_actor": "冬ノ熊肉",
    "tags": [
      "シチュエーションCD",
      "割引",
      "特典あり"
    ],
    "thumb_url": "",
    "work_url": "https://pokedora.com/products/detail.php?product_id=112534"
  },
  {
    "rank": 9,
    "product_id": "148014",
    "title": "暴漢から助けてくれたお兄さんにエロ願望を見抜かれて〇教されていますｖ【出演声優：主水Ash】",
    "voice_actor": "主水Ash",
    "tags": [
      "NEW",
      "配信限定シチュエーション"
    ],
    "thumb_url": "",
    "work_url": "https://pokedora.com/products/detail.php?product_id=148014"
  },
  {
    "rank": 10,
    "product_id": "147844",
    "title": "【えっち特化型】絶倫執着彼氏の嫉妬マシマシ膣イキSEX～100回イクまで離さない！快楽堕ち必至の連続脳イキ絶頂孕ませ体験～「あー…早くキミの事を〇したい…♪」【出演声優：一条ひらめ】",
    "voice_actor": "一条ひらめ",
    "tags": [
      "配信限定シチュエーション",
      "特典あり"
    ],
    "thumb_url": "",
    "work_url": "https://pokedora.com/products/detail.php?product_id=147844"
  },
  {
    "rank": 11,
    "product_id": "144383",
    "title": "絶頂相手は婚約者！?～今夜もイクまでハメ落ちる～【出演声優：土門熱】",
    "voice_actor": "土門熱",
    "tags": [
      "配信限定シチュエーション",
      "特典あり"
    ],
    "thumb_url": "",
    "work_url": "https://pokedora.com/products/detail.php?product_id=144383"
  },
  {
    "rank": 12,
    "product_id": "143824",
    "title": "惑溺のアンドロマリウス ～Codename: Eins～【出演声優：土門熱】",
    "voice_actor": "土門熱",
    "tags": [
      "シチュエーションCD",
      "特典あり"
    ],
    "thumb_url": "",
    "work_url": "https://pokedora.com/products/detail.php?product_id=143824"
  },
  {
    "rank": 13,
    "product_id": "142436",
    "title": "朱殷の繭 第一夜 血気之勇【出演声優：冬ノ熊肉】",
    "voice_actor": "冬ノ熊肉",
    "tags": [
      "配信限定シチュエーション",
      "特典あり"
    ],
    "thumb_url": "",
    "work_url": "https://pokedora.com/products/detail.php?product_id=142436"
  },
  {
    "rank": 14,
    "product_id": "139677",
    "title": "「そのイキ顔かわいいねv」潜入ミッション失敗→媚薬発情→ぐちゃとろ濃密ＳＥＸ→溺愛快楽堕ち【出演声優：八神仙】",
    "voice_actor": "八神仙",
    "tags": [
      "配信限定シチュエーション",
      "割引",
      "特典あり"
    ],
    "thumb_url": "",
    "work_url": "https://pokedora.com/products/detail.php?product_id=139677"
  },
  {
    "rank": 15,
    "product_id": "137500",
    "title": "【クール受け待望】えっちなバラエティ番組「イキまくり!どっぴゅんぱーてぃー」配信中【出演声優：一条ひらめ】",
    "voice_actor": "一条ひらめ",
    "tags": [
      "配信限定シチュエーション",
      "割引",
      "特典あり"
    ],
    "thumb_url": "",
    "work_url": "https://pokedora.com/products/detail.php?product_id=137500"
  },
  {
    "rank": 16,
    "product_id": "112434",
    "title": "先生、痛くしないで Vol.1 ～スーパー外科医・源慧史～【出演声優：茶介】",
    "voice_actor": "茶介",
    "tags": [
      "配信限定シチュエーション",
      "割引",
      "特典あり"
    ],
    "thumb_url": "",
    "work_url": "https://pokedora.com/products/detail.php?product_id=112434"
  },
  {
    "rank": 17,
    "product_id": "96473",
    "title": "Sweet Slowly Life 農家さんに嫁ぎました編【出演声優：冬ノ熊肉】",
    "voice_actor": "冬ノ熊肉",
    "tags": [
      "シチュエーションCD",
      "割引",
      "特典あり"
    ],
    "thumb_url": "",
    "work_url": "https://pokedora.com/products/detail.php?product_id=96473"
  },
  {
    "rank": 18,
    "product_id": "95372",
    "title": "婚約者の愛欲 -岬累也- Sweet【出演声優：猿飛総司】",
    "voice_actor": "猿飛総司",
    "tags": [
      "シチュエーションCD",
      "割引",
      "特典あり"
    ],
    "thumb_url": "",
    "work_url": "https://pokedora.com/products/detail.php?product_id=95372"
  },
  {
    "rank": 19,
    "product_id": "88518",
    "title": "義父の巨根でイカされた私…あなたごめんなさい、もう私はお義父さんのものなの セット",
    "voice_actor": "馬並ペガサス、二回戦中",
    "tags": [
      "配信限定シチュエーション"
    ],
    "thumb_url": "",
    "work_url": "https://pokedora.com/products/detail.php?product_id=88518"
  },
  {
    "rank": 20,
    "product_id": "145951",
    "title": "嘘つきコインランドリー Vol.3 夜見くんは恋がヘタすぎる【出演声優：猿飛総司】",
    "voice_actor": "猿飛総司",
    "tags": [
      "配信限定シチュエーション",
      "特典あり"
    ],
    "thumb_url": "",
    "work_url": "https://pokedora.com/products/detail.php?product_id=145951"
  },
  {
    "rank": 21,
    "product_id": "140133",
    "title": "結婚して10年たつのにまだまだ旦那さんが離してくれません ～妻にだけ過保護すぎる旦那さん～【出演声優：河村眞人】",
    "voice_actor": "河村眞人",
    "tags": [
      "配信限定シチュエーション",
      "割引",
      "特典あり"
    ],
    "thumb_url": "",
    "work_url": "https://pokedora.com/products/detail.php?product_id=140133"
  },
  {
    "rank": 22,
    "product_id": "140125",
    "title": "結婚して10年たつのにまだまだ旦那さんが離してくれません ～泣かせたがりの意地悪旦那さん～【出演声優：土門熱】",
    "voice_actor": "土門熱",
    "tags": [
      "配信限定シチュエーション",
      "割引",
      "特典あり"
    ],
    "thumb_url": "",
    "work_url": "https://pokedora.com/products/detail.php?product_id=140125"
  },
  {
    "rank": 23,
    "product_id": "140053",
    "title": "おとなり以上、恋人未満 ～完璧幼馴染・はる兄の独占欲～【出演声優：猿飛総司】",
    "voice_actor": "猿飛総司",
    "tags": [
      "配信限定シチュエーション",
      "特典あり"
    ],
    "thumb_url": "",
    "work_url": "https://pokedora.com/products/detail.php?product_id=140053"
  },
  {
    "rank": 24,
    "product_id": "139572",
    "title": "《ハイスぺ夫の重甘征服焦らしプレイ》理想的な夫婦の夜の顔【出演声優：三橋渡】",
    "voice_actor": "三橋渡",
    "tags": [
      "配信限定シチュエーション",
      "割引",
      "特典あり"
    ],
    "thumb_url": "",
    "work_url": "https://pokedora.com/products/detail.php?product_id=139572"
  },
  {
    "rank": 25,
    "product_id": "139045",
    "title": "【全編密着囁き特化】おまんこ〇教♪関西弁イジワル彼氏～バックハグでオナニー指導されながら10回イキ我慢「あー…アカン...♪気持ち良くても我慢やでー？」【出演声優：主水Ash】",
    "voice_actor": "主水Ash",
    "tags": [
      "配信限定シチュエーション",
      "特典あり"
    ],
    "thumb_url": "",
    "work_url": "https://pokedora.com/products/detail.php?product_id=139045"
  },
  {
    "rank": 26,
    "product_id": "138569",
    "title": "Bless of Stars ―水星と愛念―【出演声優：恋津田蓮也】",
    "voice_actor": "恋津田蓮也",
    "tags": [
      "配信限定シチュエーション",
      "特典あり"
    ],
    "thumb_url": "",
    "work_url": "https://pokedora.com/products/detail.php?product_id=138569"
  },
  {
    "rank": 27,
    "product_id": "138539",
    "title": "深夜残業II ～スパダリ社長・藤木礼央のプロポーズ～【出演声優：土門熱】",
    "voice_actor": "土門熱",
    "tags": [
      "配信限定シチュエーション",
      "特典あり"
    ],
    "thumb_url": "",
    "work_url": "https://pokedora.com/products/detail.php?product_id=138539"
  },
  {
    "rank": 28,
    "product_id": "138023",
    "title": "【貴女はドスケベ伝道師】 おほ声どしゅけべ言葉責め♂♀爽やかイケメン先輩とイクイクえっち!?【出演声優：一条ひらめ 近藤無月】",
    "voice_actor": "一条ひらめ、近藤無月",
    "tags": [
      "配信限定シチュエーション",
      "特典あり"
    ],
    "thumb_url": "",
    "work_url": "https://pokedora.com/products/detail.php?product_id=138023"
  },
  {
    "rank": 29,
    "product_id": "137517",
    "title": "共依存激重カイくんは溺愛おチンポ〇教でわからせたい～息もできない、失禁するほど、何度も何度もイカされる～【出演声優：一条ひらめ】",
    "voice_actor": "一条ひらめ",
    "tags": [
      "配信限定シチュエーション",
      "割引",
      "特典あり"
    ],
    "thumb_url": "",
    "work_url": "https://pokedora.com/products/detail.php?product_id=137517"
  },
  {
    "rank": 30,
    "product_id": "137483",
    "title": "【連続絶頂×純愛×受け攻め逆転】命尽きるまで豪華客船で溺愛えっち【出演声優：彩和矢】",
    "voice_actor": "彩和矢",
    "tags": [
      "配信限定シチュエーション",
      "割引",
      "特典あり"
    ],
    "thumb_url": "",
    "work_url": "https://pokedora.com/products/detail.php?product_id=137483"
  }
]